get_attachment_image/__init__.py
get_attachment_image/attachment.py
get_attachment_image-0.1.10.dist-info/METADATA
get_attachment_image-0.1.10.dist-info/WHEEL
get_attachment_image-0.1.10.dist-info/top_level.txt
get_attachment_image-0.1.10.dist-info/RECORD
