Metadata-Version: 2.1
Name: get-attachment-image
Version: 0.1.10
Summary: Paket untuk mendapatkan attachment gambar di Odoo
Home-page: https://github.com/FJ-Alam/python_project.git
Author: Fasriyah Julia Alam
Author-email: fasriyahjuliaalam@gmail.com
License: UNKNOWN
Platform: UNKNOWN
Classifier: Programming Language :: Python :: 3
Classifier: License :: OSI Approved :: MIT License
Classifier: Operating System :: OS Independent
